CHANGES.rst
MANIFEST.in
README.rst
distribute_setup.py
install.sh
setup.py
uninstall.sh
yumwat/__init__.py
yumwat/yumwat.conf
yumwat/yumwat.py
yumwat.egg-info/PKG-INFO
yumwat.egg-info/SOURCES.txt
yumwat.egg-info/dependency_links.txt
yumwat.egg-info/not-zip-safe
yumwat.egg-info/top_level.txt