Metadata-Version: 1.1
Name: yumwat
Version: 0.4.3
Summary: Prints package descriptions. A yum plugin for when you wat.
Home-page: https://github.com/oddshocks/yumwat
Author: David Gay
Author-email: oddshocks@riseup.net
License: GPL v3+
Keywords: yum plugin wat yumwat package descriptions
Platform: UNKNOWN
Classifier: Development Status :: 3 - Alpha
Classifier: Environment :: Plugins
Classifier: Intended Audience :: End Users/Desktop
Classifier: Intended Audience :: Developers
Classifier: Intended Audience :: Information Technology
Classifier: Intended Audience :: System Administrators
Classifier: License :: OSI Approved :: GNU General Public License v3 or later (GPLv3+)
Classifier: Natural Language :: English
Classifier: Programming Language :: Python :: 2.7
